plover_midi4text/__init__.py
plover_midi4text/system.py
plover_midi4text/dictionaries/midi4text_briefs.json
plover_midi4text/dictionaries/midi4text_main.json
plover_midi4text-0.0.4.dist-info/LICENSE.txt
plover_midi4text-0.0.4.dist-info/METADATA
plover_midi4text-0.0.4.dist-info/WHEEL
plover_midi4text-0.0.4.dist-info/entry_points.txt
plover_midi4text-0.0.4.dist-info/top_level.txt
plover_midi4text-0.0.4.dist-info/zip-safe
plover_midi4text-0.0.4.dist-info/RECORD
