Metadata-Version: 2.1
Name: plover-midi4text
Version: 0.0.4
Summary: Midi4Text English orthographic system implementation for Plover
Home-page: https://github.com/nsmarkop/plover_midi4text
Author: Nick Markopoulos
Author-email: nsmarkop@gmail.com
License: GNU General Public License v3 or later (GPLv3+)
Keywords: plover plover_plugin
Platform: UNKNOWN
Classifier: Development Status :: 4 - Beta
Classifier: Environment :: Plugins
Classifier: Intended Audience :: End Users/Desktop
Classifier: License :: OSI Approved :: GNU General Public License v3 or later (GPLv3+)
Classifier: Operating System :: OS Independent
Classifier: Programming Language :: Python :: 3
Requires-Dist: plover (>=4.0.0.dev7)
Requires-Dist: plover-midi (>=0.2.6)
